pywmapi/__init__.py
pywmapi/utils.py
pywmapi/auth/__init__.py
pywmapi/auth/api.py
pywmapi/auth/models.py
pywmapi/common/__init__.py
pywmapi/common/defs.py
pywmapi/common/enums.py
pywmapi/common/models.py
pywmapi/exceptions/__init__.py
pywmapi/exceptions/defs.py
pywmapi/exceptions/functions.py
pywmapi/experimental/__init__.py
pywmapi/experimental/auctions/__init__.py
pywmapi/experimental/auctions/api.py
pywmapi/experimental/auctions/models.py
pywmapi/items/__init__.py
pywmapi/items/api.py
pywmapi/items/models.py
pywmapi/lang/__init__.py
pywmapi/lang/models.py
pywmapi/liches/__init__.py
pywmapi/liches/api.py
pywmapi/liches/models.py
pywmapi/orders/__init__.py
pywmapi/orders/api.py
pywmapi/orders/models.py
pywmapi/profile/__init__.py
pywmapi/profile/api.py
pywmapi/profile/models.py
pywmapi/rivens/__init__.py
pywmapi/rivens/api.py
pywmapi/rivens/models.py
pywmapi/statistics/__init__.py
pywmapi/statistics/api.py
pywmapi/statistics/models.py
pywmapi-1.2.3.dist-info/licenses/LICENSE
pywmapi-1.2.3.dist-info/METADATA
pywmapi-1.2.3.dist-info/WHEEL
pywmapi-1.2.3.dist-info/top_level.txt
pywmapi-1.2.3.dist-info/RECORD
