Metadata-Version: 2.4
Name: pywmapi
Version: 1.2.3
Summary: API for warframe market.
Author-email: leonardodalink <linkyy2000313@gmail.com>
License: MIT License
Project-URL: Repository, https://github.com/leonardodalinky/pywmapi
Project-URL: Tracker, https://github.com/leonardodalinky/pywmapi/issues
Keywords: warframe,warframe market
Classifier: Programming Language :: Python :: 3
Classifier: License :: OSI Approved :: MIT License
Classifier: Operating System :: OS Independent
Classifier: Natural Language :: English
Requires-Python: >=3.7
License-File: LICENSE
Requires-Dist: attrs>=22
Requires-Dist: cattrs>=22
Requires-Dist: requests>=2
Requires-Dist: websocket-client>=1.2
Dynamic: license-file
